phd_scraper/.~lock.ate.csv#
phd_scraper/.~lock.santa_anita.csv#
phd_scraper/__init__.py
phd_scraper/se_historic.py
phd_scraper/se_hydrometeo.dictionary
phd_scraper/se_hydrometeo.py
phd_scraper-0.1.3.dist-info/AUTHORS.rst
phd_scraper-0.1.3.dist-info/LICENSE
phd_scraper-0.1.3.dist-info/METADATA
phd_scraper-0.1.3.dist-info/WHEEL
phd_scraper-0.1.3.dist-info/top_level.txt
phd_scraper-0.1.3.dist-info/RECORD
