Metadata-Version: 2.1
Name: phd-scraper
Version: 0.1.3
Summary: Scraping toolkit to generate PhD dataset
Home-page: https://github.com/csaybar/phd_scraper
Author: Cesar Aybar, Roy Yali, Antony Barja, Julio Contreras
Author-email: csaybar@gmail.com, ryali93@gmail.com, antony.barja8@gmail.com, julius013199@gmail.com
License: GNU General Public License v3
Keywords: scraper
Platform: UNKNOWN
Classifier: Development Status :: 2 - Pre-Alpha
Classifier: Intended Audience :: Developers
Classifier: License :: OSI Approved :: GNU General Public License v3 (GPLv3)
Classifier: Natural Language :: English
Classifier: Programming Language :: Python :: 2
Classifier: Programming Language :: Python :: 2.7
Classifier: Programming Language :: Python :: 3
Classifier: Programming Language :: Python :: 3.4
Classifier: Programming Language :: Python :: 3.5
Classifier: Programming Language :: Python :: 3.6
Classifier: Programming Language :: Python :: 3.7
